servos/__init__.py
servos/cli.py
servos/core/__init__.py
servos/core/isolation.py
servos/core/logging.py
servos/isolation/__init__.py
servos/isolation/extended_environments.py
servos/isolation/platforms/__init__.py
servos/isolation/platforms/arduino_manager.py
servos/isolation/platforms/device_detection.py
servos/isolation/platforms/micropython_manager.py
servos/isolation/platforms/platform_config.py
servos-1.0.5.dist-info/licenses/LICENSE
servos-1.0.5.dist-info/METADATA
servos-1.0.5.dist-info/WHEEL
servos-1.0.5.dist-info/entry_points.txt
servos-1.0.5.dist-info/top_level.txt
servos-1.0.5.dist-info/RECORD
