Metadata-Version: 2.4
Name: servos
Version: 1.0.5
Summary: Environment Isolation and Orchestration for Microservices
Home-page: https://github.com/tom-sapletta-com/servos
Author: Tom Sapletta
Author-email: info@softreck.dev
License: Apache-2.0
Project-URL: Documentation, https://github.com/tom-sapletta-com/servos
Project-URL: Source, https://github.com/tom-sapletta-com/servos
Project-URL: Tracker, https://github.com/tom-sapletta-com/servos/issues
Project-URL: ProServe, https://pypi.org/project/proserve/
Keywords: isolation,docker,environment,orchestration,micropython,arduino,rp2040,containers,deployment,virtualization,asyncio,embedded
Classifier: Development Status :: 4 - Beta
Classifier: Intended Audience :: Developers
Classifier: Intended Audience :: System Administrators
Classifier: License :: OSI Approved :: Apache Software License
Classifier: Operating System :: OS Independent
Classifier: Programming Language :: Python :: 3
Classifier: Programming Language :: Python :: 3.8
Classifier: Programming Language :: Python :: 3.9
Classifier: Programming Language :: Python :: 3.10
Classifier: Programming Language :: Python :: 3.11
Classifier: Programming Language :: Python :: 3.12
Classifier: Topic :: System :: Distributed Computing
Classifier: Topic :: System :: Systems Administration
Classifier: Topic :: Software Development :: Libraries :: Python Modules
Classifier: Framework :: AsyncIO
Requires-Python: >=3.8
License-File: LICENSE
Requires-Dist: aiohttp>=3.8.0
Requires-Dist: structlog>=25.0.0
Requires-Dist: rich>=14.0.0
Requires-Dist: python-dotenv>=1.0.0
Requires-Dist: PyYAML>=6.0
Requires-Dist: wmlog>=1.0.0
Provides-Extra: docker
Requires-Dist: docker>=6.0.0; extra == "docker"
Provides-Extra: micropython
Requires-Dist: adafruit-circuitpython-bundle; extra == "micropython"
Requires-Dist: esptool>=4.4; extra == "micropython"
Provides-Extra: arduino
Requires-Dist: platformio>=6.1.0; extra == "arduino"
Requires-Dist: arduino-cli>=0.30.0; extra == "arduino"
Provides-Extra: rp2040
Requires-Dist: picotool>=1.1.0; extra == "rp2040"
Requires-Dist: rp2040-tools>=0.1.0; extra == "rp2040"
Provides-Extra: testing
Requires-Dist: pytest>=7.0.0; extra == "testing"
Requires-Dist: pytest-asyncio>=0.21.0; extra == "testing"
Requires-Dist: pytest-cov>=4.0.0; extra == "testing"
Provides-Extra: development
Requires-Dist: black>=22.0.0; extra == "development"
Requires-Dist: flake8>=5.0.0; extra == "development"
Requires-Dist: mypy>=0.991; extra == "development"
Provides-Extra: all
Requires-Dist: docker>=6.0.0; extra == "all"
Requires-Dist: adafruit-circuitpython-bundle; extra == "all"
Requires-Dist: esptool>=4.4; extra == "all"
Requires-Dist: platformio>=6.1.0; extra == "all"
Requires-Dist: pytest>=7.0.0; extra == "all"
Requires-Dist: pytest-asyncio>=0.21.0; extra == "all"
Dynamic: author
Dynamic: author-email
Dynamic: classifier
Dynamic: description
Dynamic: description-content-type
Dynamic: home-page
Dynamic: keywords
Dynamic: license
Dynamic: license-file
Dynamic: project-url
Dynamic: provides-extra
Dynamic: requires-dist
Dynamic: requires-python
Dynamic: summary
